[{"name": "Trubbish", "id": 568, "base_experience": 66, "weight": 310, "height": 6, "order": 690, "slot 1": "poison", "bmi": 8.6111, "front_default": "https://raw.githubusercontent.com/PokeAPI/sprites/master/sprites/pokemon/568.png"}, {"name": "Marowak", "id": 105, "base_experience": 149, "weight": 450, "height": 10, "order": 164, "slot 1": "ground", "bmi": 4.5, "front_default": "https://raw.githubusercontent.com/PokeAPI/sprites/master/sprites/pokemon/105.png"}, {"name": "Hippowdon", "id": 450, "base_experience": 184, "weight": 3000, "height": 20, "order": 576, "slot 1": "ground", "bmi": 7.5, "front_default": "https://raw.githubusercontent.com/PokeAPI/sprites/master/sprites/pokemon/450.png"}, {"name": "Thundurus-incarnate", "id": 642, "base_experience": 290, "weight": 610, "height": 15, "order": 766, "slot 1": "electric", "slot 2": "flying", "bmi": 2.7111, "front_default": "https://raw.githubusercontent.com/PokeAPI/sprites/master/sprites/pokemon/642.png"}, {"name": "Altaria", "id": 334, "base_experience": 172, "weight": 206, "height": 11, "order": 446, "slot 1": "dragon", "slot 2": "flying", "bmi": 1.7025, "front_default": "https://raw.githubusercontent.com/PokeAPI/sprites/master/sprites/pokemon/334.png"}, {"name": "Tyranitar", "id": 248, "base_experience": 300, "weight": 2020, "height": 20, "order": 342, "slot 1": "rock", "slot 2": "dark", "bmi": 5.05, "front_default": "https://raw.githubusercontent.com/PokeAPI/sprites/master/sprites/pokemon/248.png"}, {"name": "Elekid", "id": 239, "base_experience": 72, "weight": 235, "height": 6, "order": 201, "slot 1": "electric", "bmi": 6.5278, "front_default": "https://raw.githubusercontent.com/PokeAPI/sprites/master/sprites/pokemon/239.png"}, {"name": "Whirlipede", "id": 544, "base_experience": 126, "weight": 585, "height": 12, "order": 660, "slot 1": "bug", "slot 2": "poison", "bmi": 4.0625, "front_default": "https://raw.githubusercontent.com/PokeAPI/sprites/master/sprites/pokemon/544.png"}, {"name": "Lanturn", "id": 171, "base_experience": 161, "weight": 225, "height": 12, "order": 267, "slot 1": "water", "slot 2": "electric", "bmi": 1.5625, "front_default": "https://raw.githubusercontent.com/PokeAPI/sprites/master/sprites/pokemon/171.png"}, {"name": "Skorupi", "id": 451, "base_experience": 66, "weight": 120, "height": 8, "order": 577, "slot 1": "poison", "slot 2": "bug", "bmi": 1.875, "front_default": "https://raw.githubusercontent.com/PokeAPI/sprites/master/sprites/pokemon/451.png"}, {"name": "Torchic", "id": 255, "base_experience": 62, "weight": 25, "height": 4, "order": 351, "slot 1": "fire", "bmi": 1.5625, "front_default": "https://raw.githubusercontent.com/PokeAPI/sprites/master/sprites/pokemon/255.png"}, {"name": "Excadrill", "id": 530, "base_experience": 178, "weight": 404, "height": 7, "order": 645, "slot 1": "ground", "slot 2": "steel", "bmi": 8.2449, "front_default": "https://raw.githubusercontent.com/PokeAPI/sprites/master/sprites/pokemon/530.png"}, {"name": "Croagunk", "id": 453, "base_experience": 60, "weight": 230, "height": 7, "order": 579, "slot 1": "poison", "slot 2": "fighting", "bmi": 4.6939, "front_default": "https://raw.githubusercontent.com/PokeAPI/sprites/master/sprites/pokemon/453.png"}, {"name": "Klinklang", "id": 601, "base_experience": 260, "weight": 810, "height": 6, "order": 723, "slot 1": "steel", "bmi": 22.5, "front_default": "https://raw.githubusercontent.com/PokeAPI/sprites/master/sprites/pokemon/601.png"}, {"name": "Chimchar", "id": 390, "base_experience": 62, "weight": 62, "height": 5, "order": 521, "slot 1": "fire", "bmi": 2.48, "front_default": "https://raw.githubusercontent.com/PokeAPI/sprites/master/sprites/pokemon/390.png"}, {"name": "Blissey", "id": 242, "base_experience": 635, "weight": 468, "height": 15, "order": 181, "slot 1": "normal", "bmi": 2.08, "front_default": "https://raw.githubusercontent.com/PokeAPI/sprites/master/sprites/pokemon/242.png"}, {"name": "Spiritomb", "id": 442, "base_experience": 170, "weight": 1080, "height": 10, "order": 567, "slot 1": "ghost", "slot 2": "dark", "bmi": 10.8, "front_default": "https://raw.githubusercontent.com/PokeAPI/sprites/master/sprites/pokemon/442.png"}, {"name": "Elgyem", "id": 605, "base_experience": 67, "weight": 90, "height": 5, "order": 727, "slot 1": "psychic", "bmi": 3.6, "front_default": "https://raw.githubusercontent.com/PokeAPI/sprites/master/sprites/pokemon/605.png"}, {"name": "Baltoy", "id": 343, "base_experience": 60, "weight": 215, "height": 5, "order": 456, "slot 1": "ground", "slot 2": "psychic", "bmi": 8.6, "front_default": "https://raw.githubusercontent.com/PokeAPI/sprites/master/sprites/pokemon/343.png"}, {"name": "Crawdaunt", "id": 342, "base_experience": 164, "weight": 328, "height": 11, "order": 455, "slot 1": "water", "slot 2": "dark", "bmi": 2.7107, "front_default": "https://raw.githubusercontent.com/PokeAPI/sprites/master/sprites/pokemon/342.png"}]